mujoco/__init__.py
mujoco/_callbacks.cp312-win_amd64.pyd
mujoco/_constants.cp312-win_amd64.pyd
mujoco/_enums.cp312-win_amd64.pyd
mujoco/_errors.cp312-win_amd64.pyd
mujoco/_functions.cp312-win_amd64.pyd
mujoco/_render.cp312-win_amd64.pyd
mujoco/_rollout.cp312-win_amd64.pyd
mujoco/_simulate.cp312-win_amd64.pyd
mujoco/_structs.cp312-win_amd64.pyd
mujoco/bindings_test.py
mujoco/gl_context.py
mujoco/mujoco.dll
mujoco/render_test.py
mujoco/renderer.py
mujoco/renderer_test.py
mujoco/rollout.py
mujoco/rollout_test.py
mujoco/viewer.py
mujoco/viewer_test.py
mujoco/cgl/__init__.py
mujoco/cgl/cgl.py
mujoco/egl/__init__.py
mujoco/egl/egl_ext.py
mujoco/glfw/__init__.py
mujoco/include/mujoco/mjdata.h
mujoco/include/mujoco/mjexport.h
mujoco/include/mujoco/mjmacro.h
mujoco/include/mujoco/mjmodel.h
mujoco/include/mujoco/mjplugin.h
mujoco/include/mujoco/mjrender.h
mujoco/include/mujoco/mjthread.h
mujoco/include/mujoco/mjtnum.h
mujoco/include/mujoco/mjui.h
mujoco/include/mujoco/mjvisualize.h
mujoco/include/mujoco/mjxmacro.h
mujoco/include/mujoco/mujoco.h
mujoco/osmesa/__init__.py
mujoco/plugin/elasticity.dll
mujoco/plugin/sensor.dll
mujoco_dev-2.3.8.dev570410643.dist-info/LICENSE
mujoco_dev-2.3.8.dev570410643.dist-info/LICENSES_THIRD_PARTY.md
mujoco_dev-2.3.8.dev570410643.dist-info/METADATA
mujoco_dev-2.3.8.dev570410643.dist-info/WHEEL
mujoco_dev-2.3.8.dev570410643.dist-info/top_level.txt
mujoco_dev-2.3.8.dev570410643.dist-info/RECORD
