Metadata-Version: 2.1
Name: mujoco-dev
Version: 2.3.8.dev570410643
Summary: MuJoCo Physics Simulator (unstable dev build)
Home-page: https://github.com/google-deepmind/mujoco
Author: Google DeepMind
Author-email: mujoco@deepmind.com
License: Apache License 2.0
Classifier: Development Status :: 2 - Pre-Alpha
Classifier: Intended Audience :: Developers
Classifier: Intended Audience :: Science/Research
Classifier: License :: OSI Approved :: Apache Software License
Classifier: Natural Language :: English
Classifier: Programming Language :: Python :: 3
Classifier: Programming Language :: Python :: 3.8
Classifier: Programming Language :: Python :: 3.9
Classifier: Programming Language :: Python :: 3.10
Classifier: Programming Language :: Python :: 3.11
Classifier: Topic :: Scientific/Engineering
Requires-Python: >=3.8
License-File: LICENSE
License-File: LICENSES_THIRD_PARTY.md
Requires-Dist: absl-py
Requires-Dist: glfw
Requires-Dist: numpy
Requires-Dist: pyopengl
